brain/__init__.py
brain/cli.py
brain/config.py
brain/git.py
brain/sync.py
brain/utils.py
brain/commands/__init__.py
brain/commands/add_brain.py
brain/commands/add_neuron.py
brain/commands/brain_init.py
brain/commands/checkout.py
brain/commands/clone.py
brain/commands/export.py
brain/commands/init.py
brain/commands/list.py
brain/commands/pull.py
brain/commands/push.py
brain/commands/remove_neuron.py
brain/commands/status.py
brain/commands/sync.py
git_brain-0.1.0.dist-info/LICENSE
git_brain-0.1.0.dist-info/METADATA
git_brain-0.1.0.dist-info/WHEEL
git_brain-0.1.0.dist-info/entry_points.txt
git_brain-0.1.0.dist-info/top_level.txt
git_brain-0.1.0.dist-info/RECORD
