Metadata-Version: 2.1
Name: git-brain
Version: 0.1.0
Summary: 🧠 Git extension for intelligent code sharing & synchronization between repositories without duplication.
Home-page: https://github.com/FanaticPythoner/git-brain
Author: FanaticPythoner
Author-email: nathantrudeau@hotmail.com
License: GPL-3.0
Project-URL: Homepage, https://github.com/FanaticPythoner/git-brain
Project-URL: Source Code, https://github.com/FanaticPythoner/git-brain
Project-URL: Issue Tracker, https://github.com/FanaticPythoner/git-brain/issues
Project-URL: Documentation, https://FanaticPythoner.github.io/git-brain/
Keywords: git,extension,code sharing,synchronization,modularity,version control,devops,python,cli,asset management,neuron
Classifier: Development Status :: 3 - Alpha
Classifier: Intended Audience :: Developers
Classifier: Topic :: Software Development :: Version Control
Classifier: Topic :: Software Development :: Libraries :: Python Modules
Classifier: Topic :: System :: Software Distribution
Classifier: License :: OSI Approved :: GNU General Public License v3 (GPLv3)
Classifier: Operating System :: OS Independent
Classifier: Programming Language :: Python :: 3
Classifier: Programming Language :: Python :: 3.7
Classifier: Programming Language :: Python :: 3.8
Classifier: Programming Language :: Python :: 3.9
Classifier: Programming Language :: Python :: 3.10
Classifier: Programming Language :: Python :: 3.11
Classifier: Programming Language :: Python :: 3.12
Classifier: Environment :: Console
Classifier: Natural Language :: English
Requires-Python: >=3.7
License-File: LICENSE
Requires-Dist: packaging>=20.0
